davidkhala/data/integration/__init__.py
davidkhala/data/integration/sink/__init__.py
davidkhala/data/integration/sink/arrow.py
davidkhala/data/integration/source/__init__.py
davidkhala/data/integration/source/arrow.py
davidkhala/data/integration/source/pandas.py
davidkhala_data_integration-0.0.3.dist-info/METADATA
davidkhala_data_integration-0.0.3.dist-info/WHEEL
davidkhala_data_integration-0.0.3.dist-info/RECORD
