Metadata-Version: 2.4
Name: davidkhala.data.integration
Version: 0.0.3
Summary: integration hub of davidkhala.data
Requires-Python: >=3.11
Provides-Extra: arrow
Requires-Dist: davidkhala-data-format[arrow]; extra == 'arrow'
Provides-Extra: avro
Requires-Dist: davidkhala-data-format[avro]; extra == 'avro'
Provides-Extra: gcp
Requires-Dist: davidkhala-gcp; extra == 'gcp'
Provides-Extra: pandas
Requires-Dist: davidkhala-data-frame[pandas]; extra == 'pandas'
